dial_core/__init__.py
dial_core/datasets/__init__.py
dial_core/datasets/dataset.py
dial_core/datasets/datatype/__init__.py
dial_core/datasets/datatype/categorical.py
dial_core/datasets/datatype/datatype.py
dial_core/datasets/datatype/imagearray.py
dial_core/datasets/datatype/imagepath.py
dial_core/datasets/datatype/numeric.py
dial_core/datasets/datatype/numericarray.py
dial_core/datasets/io/__init__.py
dial_core/datasets/io/dataset_io.py
dial_core/datasets/io/ttv_sets_io.py
dial_core/datasets/io/ttv_sets_loader.py
dial_core/datasets/ttv_sets.py
dial_core/node_editor/__init__.py
dial_core/node_editor/input_port.py
dial_core/node_editor/node.py
dial_core/node_editor/node_registry.py
dial_core/node_editor/output_port.py
dial_core/node_editor/port.py
dial_core/node_editor/scene.py
dial_core/notebook/__init__.py
dial_core/notebook/node_cells.py
dial_core/notebook/node_cells_registry.py
dial_core/notebook/notebook_project_generator.py
dial_core/plugin/__init__.py
dial_core/plugin/plugin.py
dial_core/plugin/plugin_manager.py
dial_core/project/__init__.py
dial_core/project/project.py
dial_core/project/project_manager.py
dial_core/utils/__init__.py
dial_core/utils/enum.py
dial_core/utils/exceptions.py
dial_core/utils/initialization.py
dial_core/utils/log/__init__.py
dial_core/utils/log/log.py
dial_core/utils/log/log_decorator.py
dial_core/utils/timer.py
dial_core/utils/traverse.py
dial_core-0.21a0.dist-info/LICENSE
dial_core-0.21a0.dist-info/WHEEL
dial_core-0.21a0.dist-info/METADATA
dial_core-0.21a0.dist-info/RECORD
