Metadata-Version: 2.1
Name: dial-core
Version: 0.21a0
Summary: Deep Learning, node-based framework
Home-page: https://github.com/dial-app/dial-core
License: GPL-3.0-only
Keywords: deep-learning
Author: David Afonso
Author-email: davafons@gmail.com
Requires-Python: >=3.6.0,<=3.8.3
Classifier: License :: OSI Approved :: GNU General Public License v3 (GPLv3)
Classifier: Programming Language :: Python :: 3
Classifier: Programming Language :: Python :: 3.6
Classifier: Programming Language :: Python :: 3.7
Classifier: Programming Language :: Python :: 3.8
Requires-Dist: dependency-injector (>=3.15.6,<4.0.0)
Requires-Dist: nbformat (>=5.0.5,<6.0.0)
Requires-Dist: pillow (>=7.1.2,<8.0.0)
Requires-Dist: rope (>=0.16.0,<0.17.0)
Requires-Dist: tensorflow (>=2.2.0,<3.0.0)
Requires-Dist: toml (>=0.10.0,<0.11.0)
Project-URL: Repository, https://github.com/dial-app/dial-core
